lib_ms_api/__init__.py
lib_ms_api/abstract_controller.py
lib_ms_api/abstract_dto.py
lib_ms_api/abstract_repository.py
lib_ms_api/abstract_service.py
lib_ms_api/date_util.py
lib_ms_api/settings.py
lib_ms_api-1.0.0.dist-info/METADATA
lib_ms_api-1.0.0.dist-info/WHEEL
lib_ms_api-1.0.0.dist-info/top_level.txt
lib_ms_api-1.0.0.dist-info/RECORD
