Metadata-Version: 2.1
Name: lib-ms-api
Version: 1.0.0
Summary: A Python library to build simple Microservices
Home-page: UNKNOWN
Author: Uedson Reis
License: ISC
Platform: UNKNOWN
